dag_modelling/__init__.py
dag_modelling/bundles/__init__.py
dag_modelling/bundles/file_reader.py
dag_modelling/bundles/load_array.py
dag_modelling/bundles/load_graph.py
dag_modelling/bundles/load_hist.py
dag_modelling/bundles/load_parameters.py
dag_modelling/bundles/load_record.py
dag_modelling/bundles/make_y_parameters_for_x.py
dag_modelling/core/__init__.py
dag_modelling/core/data_descriptor.py
dag_modelling/core/edges.py
dag_modelling/core/exception.py
dag_modelling/core/flags_descriptor.py
dag_modelling/core/global_parameters.py
dag_modelling/core/graph.py
dag_modelling/core/graph_base.py
dag_modelling/core/input.py
dag_modelling/core/input_strategy.py
dag_modelling/core/iter.py
dag_modelling/core/labels.py
dag_modelling/core/meta_node.py
dag_modelling/core/node.py
dag_modelling/core/node_base.py
dag_modelling/core/output.py
dag_modelling/core/storage.py
dag_modelling/core/types.py
dag_modelling/core/type_functions/__init__.py
dag_modelling/core/type_functions/axes_type_functions.py
dag_modelling/core/type_functions/copy_type_functions.py
dag_modelling/core/type_functions/input_type_functions.py
dag_modelling/core/type_functions/output_type_functions.py
dag_modelling/core/type_functions/tools_for_type_functions.py
dag_modelling/lib/__init__.py
dag_modelling/lib/arithmetic.py
dag_modelling/lib/exponential.py
dag_modelling/lib/trigonometry.py
dag_modelling/lib/abstract/__init__.py
dag_modelling/lib/abstract/block_to_one_node.py
dag_modelling/lib/abstract/many_to_one_node.py
dag_modelling/lib/abstract/one_to_one_node.py
dag_modelling/lib/axis/__init__.py
dag_modelling/lib/axis/bin_center.py
dag_modelling/lib/axis/bin_width.py
dag_modelling/lib/axis/mesh_to_edges.py
dag_modelling/lib/calculus/__init__.py
dag_modelling/lib/calculus/jacobian.py
dag_modelling/lib/common/__init__.py
dag_modelling/lib/common/array.py
dag_modelling/lib/common/cache.py
dag_modelling/lib/common/concatenation.py
dag_modelling/lib/common/copy.py
dag_modelling/lib/common/dummy.py
dag_modelling-0.14.3.dist-info/licenses/LICENSE
dag_modelling-0.14.3.dist-info/METADATA
dag_modelling-0.14.3.dist-info/WHEEL
dag_modelling-0.14.3.dist-info/top_level.txt
dag_modelling-0.14.3.dist-info/RECORD
