Metadata-Version: 2.4
Name: dag-modelling
Version: 0.14.3
Summary: The dag-modelling package is a python implementation of the dataflow programming with the lazy graph evaluation.
Author-email: DAGModelling Team <dagflow@jinr.ru>
Maintainer-email: DAGModelling Team <dagflow@jinr.ru>
License-Expression: MIT
Project-URL: Bug Tracker, https://github.com/dagflow-team/dag-modelling/issues
Project-URL: DAGModelling Team, https://github.com/dagflow-team
Project-URL: documentation, https://github.com/dagflow-team/dag-modelling/wiki
Project-URL: homepage, https://github.com/dagflow-team/dag-modelling
Project-URL: repository, https://github.com/dagflow-team/dag-modelling
Classifier: Programming Language :: Python :: 3 :: Only
Classifier: Programming Language :: Python :: 3.11
Classifier: Programming Language :: Python :: 3.12
Classifier: Programming Language :: Python :: 3.13
Requires-Python: >=3.11
License-File: LICENSE
Requires-Dist: contextlib2
Requires-Dist: h5py
Requires-Dist: latexdatax
Requires-Dist: matplotlib
Requires-Dist: nested-mapping>=0.11
Requires-Dist: numba
Requires-Dist: numpy
Requires-Dist: ordered-set
Requires-Dist: pandas
Requires-Dist: plotille
Requires-Dist: pyyaml
Requires-Dist: schema
Requires-Dist: scipy
Requires-Dist: tabulate
Requires-Dist: uproot
Provides-Extra: extra
Requires-Dist: pygraphviz; extra == "extra"
Provides-Extra: test
Requires-Dist: coverage; extra == "test"
Requires-Dist: pygraphviz; extra == "test"
Requires-Dist: pytest; extra == "test"
Requires-Dist: pytest-cov; extra == "test"
Dynamic: license-file
